to_jsonl_zxw/__init__.py
to_jsonl_zxw/to_jsonl.py
to_jsonl_zxw-0.0.1.dist-info/METADATA
to_jsonl_zxw-0.0.1.dist-info/WHEEL
to_jsonl_zxw-0.0.1.dist-info/top_level.txt
to_jsonl_zxw-0.0.1.dist-info/RECORD
